Metadata-Version: 2.1
Name: resnet50-pynq
Version: 1.1
Summary: Quantized dataflow implementation of ResNet50 on Alveo
Home-page: https://github.com/Xilinx/ResNet50-PYNQ
Author: Lucian Petrica
License: BSD 3-Clause
Download-URL: https://github.com/Xilinx/ResNet50-PYNQ
Platform: UNKNOWN
Requires-Python: >=3.5.2
